{
  "swagger": "2.0",
  "info": {
    "title": "dummy/v1/dummy.proto",
    "version": "version not set"
  },
  "tags": [
    {
      "name": "GeeterService"
    },
    {
      "name": "EchoService"
    }
  ],
  "consumes": [
    "application/json"
  ],
  "produces": [
    "application/json"
  ],
  "paths": {
    "/v1/messsage": {
      "post": {
        "operationId": "GeeterService_SayHello",
        "responses": {
          "200": {
            "description": "A successful response.",
            "schema": {
              "$ref": "#/definitions/v1SayHelloResponse"
            }
          },
          "default": {
            "description": "An unexpected error response.",
            "schema": {
              "$ref": "#/definitions/rpcStatus"
            }
          }
        },
        "parameters": [
          {
            "name": "body",
            "in": "body",
            "required": true,
            "schema": {
              "$ref": "#/definitions/v1SayHelloRequest"
            }
          }
        ],
        "tags": [
          "GeeterService"
        ]
      }
    }
  },
  "definitions": {
    "protobufAny": {
      "type": "object",
      "properties": {
        "@type": {
          "type": "string"
        }
      },
      "additionalProperties": {}
    },
    "rpcStatus": {
      "type": "object",
      "properties": {
        "code": {
          "type": "integer",
          "format": "int32"
        },
        "message": {
          "type": "string"
        },
        "details": {
          "type": "array",
          "items": {
            "type": "object",
            "$ref": "#/definitions/protobufAny"
          }
        }
      }
    },
    "v1EchoResponse": {
      "type": "object",
      "properties": {
        "message": {
          "type": "string"
        }
      }
    },
    "v1SayHelloRequest": {
      "type": "object",
      "properties": {
        "name": {
          "type": "string"
        }
      }
    },
    "v1SayHelloResponse": {
      "type": "object",
      "properties": {
        "message": {
          "type": "string"
        }
      }
    }
  }
}
